phone_data/__init__.py
phone_data/country_codes.html
phone_data/main.py
py_phone_data-0.0.5.dist-info/LICENSE
py_phone_data-0.0.5.dist-info/METADATA
py_phone_data-0.0.5.dist-info/WHEEL
py_phone_data-0.0.5.dist-info/entry_points.txt
py_phone_data-0.0.5.dist-info/top_level.txt
py_phone_data-0.0.5.dist-info/RECORD
