Metadata-Version: 2.1
Name: py-phone-data
Version: 0.0.5
Summary: Simple phone info
Home-page: https://github.com/IsaacWritesCodeGithub/py-phone-data
Author: IsaacWritesCode
Author-email: isaacwritescode7@gmail.com
License: UNKNOWN
Platform: UNKNOWN
License-File: LICENSE
Requires-Dist: lxml (>=4.8.0)
Requires-Dist: Gooey (>=1.0.8.1)
Requires-Dist: pandas (>=1.4.2)
Requires-Dist: requests (>=2.27.1)
